git_monorepo
