Metadata-Version: 1.0
Name: git-monorepo
Version: 1.9.1
Summary: git_monorepo
Home-page: UNKNOWN
Author: Bogdan Mustiata
Author-email: bogdan.mustiata@gmail.com
License: BSD
Platform: UNKNOWN
